pyhatchbabyrest/__init__.py
pyhatchbabyrest/constants.py
pyhatchbabyrest/pyhatchbabyrest.py
pyhatchbabyrest/pyhatchbabyrestasync.py
pyhatchbabyrest-2.1.0.dist-info/LICENSE
pyhatchbabyrest-2.1.0.dist-info/METADATA
pyhatchbabyrest-2.1.0.dist-info/WHEEL
pyhatchbabyrest-2.1.0.dist-info/top_level.txt
pyhatchbabyrest-2.1.0.dist-info/RECORD
