Metadata-Version: 2.1
Name: pyhatchbabyrest
Version: 2.1.0
Summary: Python library to control Hatch Baby Rest devices
Home-page: https://github.com/kjoconnor/pyhatchbabyrest
Author: Kevin O'Connor
Author-email: kjoconnor@gmail.com
Classifier: Programming Language :: Python :: 3
Classifier: License :: OSI Approved :: MIT License
Classifier: Operating System :: Unix
Classifier: Topic :: Home Automation
Requires-Python: >=3.5
License-File: LICENSE
Requires-Dist: bleak
Requires-Dist: pygatt
